<?xml version="1.0" encoding="utf-8" ?>
<dwsync>
<file name="index.htm" server="113.10.242.28/wwwroot/" local="130127260536196487" remote="130072047000000000" Dst="0" />
<file name="misc_buyinvitecode.php" server="113.10.242.28/wwwroot/" local="130127260540177156" remote="130072047000000000" Dst="0" />
<file name="misc_diyhelp.php" server="113.10.242.28/wwwroot/" local="130127260541327123" remote="130072047000000000" Dst="0" />
<file name="misc_error.php" server="113.10.242.28/wwwroot/" local="130127260542137372" remote="130072047000000000" Dst="0" />
<file name="misc_faq.php" server="113.10.242.28/wwwroot/" local="130127260542997463" remote="130072047000000000" Dst="0" />
<file name="misc_imgcropper.php" server="113.10.242.28/wwwroot/" local="130127260544597692" remote="130072047000000000" Dst="0" />
<file name="misc_getatuser.php" server="113.10.242.28/wwwroot/" local="130127260545082587" remote="130072047000000000" Dst="0" />
<file name="misc_initsys.php" server="113.10.242.28/wwwroot/" local="130127260545782609" remote="130072047000000000" Dst="0" />
<file name="misc_invite.php" server="113.10.242.28/wwwroot/" local="130127260547057646" remote="130072047000000000" Dst="0" />
<file name="misc_manyou.php" server="113.10.242.28/wwwroot/" local="130127260547582678" remote="130072047000000000" Dst="0" />
<file name="misc_mobile.php" server="113.10.242.28/wwwroot/" local="130127260548907734" remote="130072047000000000" Dst="0" />
<file name="misc_patch.php" server="113.10.242.28/wwwroot/" local="130127260549082746" remote="130072047000000000" Dst="0" />
<file name="misc_ranklist.php" server="113.10.242.28/wwwroot/" local="130127260550502863" remote="130072047000000000" Dst="0" />
<file name="misc_seccode.php" server="113.10.242.28/wwwroot/" local="130127260550522877" remote="130072047000000000" Dst="0" />
<file name="misc_report.php" server="113.10.242.28/wwwroot/" local="130127260551022944" remote="130072047000000000" Dst="0" />
<file name="misc_secqaa.php" server="113.10.242.28/wwwroot/" local="130127260552493128" remote="130072047000000000" Dst="0" />
<file name="misc_signin.php" server="113.10.242.28/wwwroot/" local="130127260553243207" remote="130072047000000000" Dst="0" />
<file name="misc_stat.php" server="113.10.242.28/wwwroot/" local="130127260554203341" remote="130072047000000000" Dst="0" />
<file name="misc_swfupload.php" server="113.10.242.28/wwwroot/" local="130127260555223467" remote="130072047000000000" Dst="0" />
<file name="misc_tag.php" server="113.10.242.28/wwwroot/" local="130127260555403486" remote="130072047000000000" Dst="0" />
<file name="misc_userstatus.php" server="113.10.242.28/wwwroot/" local="130127260555923548" remote="130072047000000000" Dst="0" />
</dwsync>