<?xml version="1.0" encoding="utf-8" ?>
<dwsync>
<file name="db.class.php" server="113.10.242.28/wwwroot/" local="130127263409186024" remote="130072047000000000" Dst="0" />
<file name="index.htm" server="113.10.242.28/wwwroot/" local="130127263409706077" remote="130072047000000000" Dst="0" />
<file name="sendmail.inc.php" server="113.10.242.28/wwwroot/" local="130127263411376293" remote="130072047000000000" Dst="0" />
<file name="seccode.class.php" server="113.10.242.28/wwwroot/" local="130127263411566473" remote="130072047000000000" Dst="0" />
<file name="template.class.php" server="113.10.242.28/wwwroot/" local="130127263411926578" remote="130072047000000000" Dst="0" />
<file name="uccode.class.php" server="113.10.242.28/wwwroot/" local="130127263413274304" remote="130072047000000000" Dst="0" />
<file name="xml.class.php" server="113.10.242.28/wwwroot/" local="130127263414049354" remote="130072047000000000" Dst="0" />
<file name="upload.class.php" server="113.10.242.28/wwwroot/" local="130127263414449363" remote="130072047000000000" Dst="0" />
</dwsync>