<?xml version="1.0" encoding="utf-8" ?>
<dwsync>
<file name="0.gif" server="113.10.242.28/wwwroot/" local="130127262229759615" remote="130072047000000000" Dst="0" />
<file name="1.gif" server="113.10.242.28/wwwroot/" local="130127262229759615" remote="130072047000000000" Dst="0" />
<file name="10.gif" server="113.10.242.28/wwwroot/" local="130127262232239915" remote="130072047000000000" Dst="0" />
<file name="11.gif" server="113.10.242.28/wwwroot/" local="130127262232249909" remote="130072047000000000" Dst="0" />
<file name="12.gif" server="113.10.242.28/wwwroot/" local="130127262232279918" remote="130072047000000000" Dst="0" />
<file name="13.gif" server="113.10.242.28/wwwroot/" local="130127262234170168" remote="130072047000000000" Dst="0" />
<file name="14.gif" server="113.10.242.28/wwwroot/" local="130127262234170168" remote="130072047000000000" Dst="0" />
<file name="15.gif" server="113.10.242.28/wwwroot/" local="130127262234400191" remote="130072047000000000" Dst="0" />
<file name="2.gif" server="113.10.242.28/wwwroot/" local="130127262235900370" remote="130072047000000000" Dst="0" />
<file name="3.gif" server="113.10.242.28/wwwroot/" local="130127262236220580" remote="130072047000000000" Dst="0" />
<file name="4.gif" server="113.10.242.28/wwwroot/" local="130127262236630469" remote="130072047000000000" Dst="0" />
<file name="5.gif" server="113.10.242.28/wwwroot/" local="130127262237861991" remote="130072047000000000" Dst="0" />
<file name="6.gif" server="113.10.242.28/wwwroot/" local="130127262238082007" remote="130072047000000000" Dst="0" />
<file name="7.gif" server="113.10.242.28/wwwroot/" local="130127262238562100" remote="130072047000000000" Dst="0" />
<file name="8.gif" server="113.10.242.28/wwwroot/" local="130127262240096262" remote="130072047000000000" Dst="0" />
<file name="9.gif" server="113.10.242.28/wwwroot/" local="130127262241486436" remote="130072047000000000" Dst="0" />
<file name="index.htm" server="113.10.242.28/wwwroot/" local="130127262238572095" remote="130072047000000000" Dst="0" />
</dwsync>