<?xml version="1.0" encoding="utf-8" ?>
<dwsync>
<file name="01.gif" server="113.10.242.28/wwwroot/" local="130127262070680176" remote="130072047000000000" Dst="0" />
<file name="02.gif" server="113.10.242.28/wwwroot/" local="130127262071380254" remote="130072047000000000" Dst="0" />
<file name="04.gif" server="113.10.242.28/wwwroot/" local="130127262072850286" remote="130072047000000000" Dst="0" />
<file name="05.gif" server="113.10.242.28/wwwroot/" local="130127262074050443" remote="130072047000000000" Dst="0" />
<file name="06.gif" server="113.10.242.28/wwwroot/" local="130127262075390650" remote="130072047000000000" Dst="0" />
<file name="07.gif" server="113.10.242.28/wwwroot/" local="130127262076761017" remote="130072047000000000" Dst="0" />
<file name="03.gif" server="113.10.242.28/wwwroot/" local="130127262077850923" remote="130072047000000000" Dst="0" />
<file name="08.gif" server="113.10.242.28/wwwroot/" local="130127262079081083" remote="130072047000000000" Dst="0" />
<file name="09.gif" server="113.10.242.28/wwwroot/" local="130127262080264316" remote="130072047000000000" Dst="0" />
<file name="10.gif" server="113.10.242.28/wwwroot/" local="130127262081110048" remote="130072047000000000" Dst="0" />
<file name="11.gif" server="113.10.242.28/wwwroot/" local="130127262081850145" remote="130072047000000000" Dst="0" />
<file name="12.gif" server="113.10.242.28/wwwroot/" local="130127262083092887" remote="130072047000000000" Dst="0" />
<file name="13.gif" server="113.10.242.28/wwwroot/" local="130127262083982993" remote="130072047000000000" Dst="0" />
<file name="14.gif" server="113.10.242.28/wwwroot/" local="130127262085112977" remote="130072047000000000" Dst="0" />
<file name="15.gif" server="113.10.242.28/wwwroot/" local="130127262086253114" remote="130072047000000000" Dst="0" />
<file name="16.gif" server="113.10.242.28/wwwroot/" local="130127262087913323" remote="130072047000000000" Dst="0" />
<file name="index.htm" server="113.10.242.28/wwwroot/" local="130127262085122981" remote="130072047000000000" Dst="0" />
</dwsync>